<?xml version="1.0" encoding="ISO-8859-1" ?>

<!-- contains the ejb cartridge metafacade mappings -->
<metafacades namespace="ejb">
	<metafacade 
		metaobjectClass="org.omg.uml.foundation.core.Operation$Impl"
		metafacadeClass="org.andromda.cartridges.ejb.metadecorators.uml14.EJBFinderMethodDecoratorImpl">
		<stereotype>FinderMethod</stereotype>
	</metafacade>
	<metafacade 
		metaobjectClass="org.omg.uml.foundation.core.Attribute$Impl"
		metafacadeClass="org.andromda.cartridges.ejb.metadecorators.uml14.EJBPrimaryKeyDecoratorImpl">
		<stereotype>PrimaryKey</stereotype>
		<property reference="sqlMappings"/>
		<property reference="jdbcMappings"/>
	</metafacade>
	<metafacade 
		metaobjectClass="org.omg.uml.foundation.core.UmlClass$Impl"
		metafacadeClass="org.andromda.cartridges.ejb.metadecorators.uml14.EJBEntityDecoratorImpl">
		<property reference="maxSqlNameLength"/>
		<!-- <stereotype>Entity</stereotype> -->
	</metafacade>
	<metafacade 
		metaobjectClass="org.omg.uml.foundation.core.Interface$Impl"
		metafacadeClass="org.andromda.cartridges.ejb.metadecorators.uml14.EJBEntityDecoratorImpl">
		<property reference="maxSqlNameLength"/>
		<!-- <stereotype>Entity</stereotype> -->
	</metafacade>
	<metafacade 
		metaobjectClass="org.omg.uml.foundation.core.AssociationEnd$Impl"
		metafacadeClass="org.andromda.cartridges.ejb.metadecorators.uml14.EJBAssociationEndDecoratorImpl">
		<context>org.andromda.cartridges.ejb.metadecorators.uml14.EJBEntityDecoratorImpl</context>
		<property reference="foreignKeySuffix"/>
	</metafacade>			
	<metafacade 
		metaobjectClass="org.omg.uml.foundation.core.Attribute$Impl"
		metafacadeClass="org.andromda.core.metadecorators.uml14.EntityAttributeDecoratorImpl">
		<context>org.andromda.cartridges.ejb.metadecorators.uml14.EJBEntityDecoratorImpl</context>
		<property reference="sqlMappings"/>
		<property reference="jdbcMappings"/>
	</metafacade>		
</metafacades>